CoDrone_mini/__init__.py
CoDrone_mini/crc.py
CoDrone_mini/drone.py
CoDrone_mini/protocol.py
CoDrone_mini/receiver.py
CoDrone_mini/storage.py
CoDrone_mini/system.py
CoDrone_mini/update.py
CoDrone_mini-0.17.dist-info/DESCRIPTION.rst
CoDrone_mini-0.17.dist-info/METADATA
CoDrone_mini-0.17.dist-info/RECORD
CoDrone_mini-0.17.dist-info/WHEEL
CoDrone_mini-0.17.dist-info/metadata.json
CoDrone_mini-0.17.dist-info/top_level.txt
