Metadata-Version: 2.0
Name: CoDrone-mini
Version: 0.17
Summary: Python library for control CoDrone mini
Home-page: UNKNOWN
Author: robolink
Author-email: admin@robolink.com
License: UNKNOWN
Platform: UNKNOWN
Requires-Python: >=3.3
Requires-Dist: colorama
Requires-Dist: numpy
Requires-Dist: pyserial
